inquirer_textual/InquirerApp.py
inquirer_textual/__init__.py
inquirer_textual/prompts.py
inquirer_textual/version.py
inquirer_textual/common/AppConfig.py
inquirer_textual/common/Choice.py
inquirer_textual/common/ChoiceCheckboxLabel.py
inquirer_textual/common/ChoiceLabel.py
inquirer_textual/common/InquirerHeader.py
inquirer_textual/common/InquirerResult.py
inquirer_textual/common/PromptMessage.py
inquirer_textual/common/Shortcut.py
inquirer_textual/common/StandardTheme.py
inquirer_textual/common/__init__.py
inquirer_textual/widgets/InquirerCheckbox.py
inquirer_textual/widgets/InquirerConfirm.py
inquirer_textual/widgets/InquirerEditor.py
inquirer_textual/widgets/InquirerMulti.py
inquirer_textual/widgets/InquirerNumber.py
inquirer_textual/widgets/InquirerPath.py
inquirer_textual/widgets/InquirerPattern.py
inquirer_textual/widgets/InquirerSecret.py
inquirer_textual/widgets/InquirerSelect.py
inquirer_textual/widgets/InquirerText.py
inquirer_textual/widgets/InquirerWidget.py
inquirer_textual/widgets/__init__.py
inquirer_textual-0.3.0.dist-info/METADATA
inquirer_textual-0.3.0.dist-info/WHEEL
inquirer_textual-0.3.0.dist-info/licenses/LICENSE
inquirer_textual-0.3.0.dist-info/RECORD
