Metadata-Version: 2.4
Name: inquirer-textual
Version: 0.3.0
Summary: Inquirer based on Textual
Project-URL: Changelog, https://github.com/robvanderleek/inquirer-textual/blob/master/CHANGELOG.md
Project-URL: Documentation, https://robvanderleek.github.io/inquirer-textual/
Project-URL: Source, https://github.com/robvanderleek/inquirer-textual
Author-email: Rob van der Leek <robvanderleek@gmail.com>
License-Expression: GPL-3.0-or-later
License-File: LICENSE
Requires-Python: <3.15,>=3.9
Requires-Dist: textual>=7.1.0
Provides-Extra: examples
Requires-Dist: textual-slider>=0.2.0; extra == 'examples'
